extract_social_media/__init__.py
extract_social_media-0.4.0.dist-info/DESCRIPTION.rst
extract_social_media-0.4.0.dist-info/METADATA
extract_social_media-0.4.0.dist-info/RECORD
extract_social_media-0.4.0.dist-info/WHEEL
extract_social_media-0.4.0.dist-info/metadata.json
extract_social_media-0.4.0.dist-info/top_level.txt
