Metadata-Version: 2.0
Name: extract-social-media
Version: 0.4.0
Summary: Extract social media links from websites
Home-page: https://github.com/fluquid/extract-social-media
Author: Johannes Ahlmann
Author-email: johannes@fluquid.com
License: MIT
Keywords: extract-social-media
Platform: UNKNOWN
Classifier: Development Status :: 2 - Pre-Alpha
Classifier: Intended Audience :: Developers
Classifier: License :: OSI Approved :: MIT License
Classifier: Natural Language :: English
Classifier: Programming Language :: Python :: 2
Classifier: Programming Language :: Python :: 2.7
Classifier: Programming Language :: Python :: 3
Classifier: Programming Language :: Python :: 3.4
Classifier: Programming Language :: Python :: 3.5
Requires-Dist: lxml
Requires-Dist: requests
Requires-Dist: html-to-etree
Requires-Dist: six
